[
  {
    "id": "json_token",
    "category": "api_keys",
    "keywords": [
      "json",
      "with",
      "encoded"
    ],
    "regex": "(?:[{[,][ \\t]*[ \\t\\r\\n]*\"(?i)[a-z_-]*(?:secret|service_pass(wd|word|code|phrase)|pass(?:wd|word|code|phrase)?|key|token)\"[ \\t]*:[ \\t]*\")([0-9a-f]{32}|[0-9a-f]{40}|[0-9a-f]{64})(?:\"[ \\t\\r\\n]*[,}\\]])",
    "risk": "high",
    "entropy": 3.5
  },
  {
    "id": "uuidv4_bearer_token",
    "category": "cloud_credentials",
    "keywords": [
      "uuidv4",
      "bearer",
      "token"
    ],
    "regex": "(?:(\\b|\\A)(?i)Bearer[ ])([a-f0-9]{8}-[a-f0-9]{4}-4[a-f0-9]{3}-[89ab][a-f0-9]{3}-[a-f0-9]{12})(?:\\b|\\z)",
    "risk": "high",
    "entropy": 3.5
  },
  {
    "id": "terraformcloud_api_token",
    "category": "api_key",
    "keywords": [
      "terraformcloud"
    ],
    "regex": "\\b([A-Za-z0-9]{14}.atlasv1.[A-Za-z0-9]{67})\\b",
    "risk": "high",
    "entropy": 3.5
  },
  {
    "id": "okta_token_precise",
    "category": "private_keys",
    "keywords": [
      "okta",
      "precise"
    ],
    "regex": "(?:(\\bSSWS\\s{1,5}|(?i)okta[_-]?(api[_-]?)?(token|key|secret)\\s{0,28}([:=]|[=-]>|to|[!=]={1,2}|<>)\\s{0,28}['\"`]?))(0{2}[0-9A-Za-z_-]{40})(?:\\z|[^0-9A-Za-z_+/=-])",
    "risk": "high",
    "entropy": 3.5
  },
  {
    "id": "asana_access_token",
    "category": "api_key",
    "keywords": [
      "asana"
    ],
    "regex": "(?i)(?:asana)(?:.|[\\n\\r]){0,40}\\b([0-9]{1,}\\/[0-9]{16,}:[A-Za-z0-9]{32,})\\b",
    "risk": "high",
    "entropy": 3.5
  },
  {
    "id": "auth0_api_token",
    "category": "api_key",
    "keywords": [
      "auth0"
    ],
    "regex": "(?i)(?:auth0)(?:.|[\\n\\r]){0,40}\\b(ey[a-zA-Z0-9._-]+)\\b",
    "risk": "high",
    "entropy": 3.5
  },
  {
    "id": "auth0_domain_url",
    "category": "api_key",
    "keywords": [
      "auth0"
    ],
    "regex": "([a-zA-Z0-9\\-]{2,16}\\.[a-zA-Z0-9_-]{2,3}\\.auth0\\.com)",
    "risk": "high",
    "entropy": 3.5
  },
  {
    "id": "auth0_oauth_client_id",
    "category": "api_key",
    "keywords": [
      "auth0"
    ],
    "regex": "(?i)(?:auth0)(?:.|[\\n\\r]){0,40}\\b([a-zA-Z0-9_-]{32,60})\\b",
    "risk": "high",
    "entropy": 3.5
  },
  {
    "id": "auth0_oauth_client_secret",
    "category": "api_key",
    "keywords": [
      "auth0"
    ],
    "regex": "\\b([a-zA-Z0-9_-]{64,})\\b",
    "risk": "high",
    "entropy": 3.5
  },
  {
    "id": "auth0_oauth_domain_url",
    "category": "api_key",
    "keywords": [
      "auth0"
    ],
    "regex": "\\b([a-zA-Z0-9][a-zA-Z0-9._-]*auth0\\.com)\\b",
    "risk": "high",
    "entropy": 3.5
  },
  {
    "id": "avaza_api_token",
    "category": "api_key",
    "keywords": [
      "avaza"
    ],
    "regex": "(?i)(?:avaza)(?:.|[\\n\\r]){0,40}\\b([0-9]+-[0-9a-f]{40})\\b",
    "risk": "high",
    "entropy": 3.5
  },
  {
    "id": "bitly_access_token",
    "category": "api_key",
    "keywords": [
      "bitly"
    ],
    "regex": "(?i)(?:bitly)(?:.|[\\n\\r]){0,40}\\b([a-zA-Z-0-9]{40})\\b",
    "risk": "high",
    "entropy": 3.5
  },
  {
    "id": "clickup_personal_token",
    "category": "api_key",
    "keywords": [
      "clickup"
    ],
    "regex": "(?i)(?:clickup)(?:.|[\\n\\r]){0,40}\\b(pk_[0-9]{8}_[0-9A-Z]{32})\\b",
    "risk": "high",
    "entropy": 3.5
  },
  {
    "id": "cloudflare_api_token",
    "category": "api_key",
    "keywords": [
      "cloudflare"
    ],
    "regex": "(?i)(?:cloudflare)(?:.|[\\n\\r]){0,40}\\b([A-Za-z0-9_-]{40})\\b",
    "risk": "high",
    "entropy": 3.5
  },
  {
    "id": "contentful_api_personal_token",
    "category": "api_key",
    "keywords": [
      "contentful"
    ],
    "regex": "\\b([CFPAT\\-a-zA-Z-0-9]{49})\\b",
    "risk": "high",
    "entropy": 3.5
  },
  {
    "id": "discord_api_token",
    "category": "api_key",
    "keywords": [
      "discord"
    ],
    "regex": "(?i)(?:discord)(?:.|[\\n\\r]){0,40}\\b([A-Za-z0-9_-]{24}\\.[A-Za-z0-9_-]{6}\\.[A-Za-z0-9_-]{27})\\b",
    "risk": "high"
  },
  {
    "id": "facebook_oauth_id",
    "category": "api_key",
    "keywords": [
      "facebook"
    ],
    "regex": "(?i)(?:facebook)(?:.|[\\n\\r]){0,40}\\b([0-9]{15,18})\\b",
    "risk": "high",
    "entropy": 3.5
  },
  {
    "id": "facebook_oauth_secret",
    "category": "api_key",
    "keywords": [
      "facebook"
    ],
    "regex": "(?i)(?:facebook)(?:.|[\\n\\r]){0,40}\\b([A-Za-z0-9]{32})\\b",
    "risk": "high",
    "entropy": 3.5
  },
  {
    "id": "facebook_access_token",
    "category": "api_key",
    "keywords": [
      "facebook"
    ],
    "regex": "EAACEdEose0cBA[0-9A-Za-z]+",
    "risk": "high",
    "entropy": 3.5
  },
  {
    "id": "fastly_api_token",
    "category": "api_key",
    "keywords": [
      "fastly"
    ],
    "regex": "(?i)(?:fastly)(?:.|[\\n\\r]){0,40}\\b([A-Za-z0-9_-]{32})\\b",
    "risk": "high",
    "entropy": 3.5
  },
  {
    "id": "figma_access_token",
    "category": "api_key",
    "keywords": [
      "figma"
    ],
    "regex": "(?i)(?:figma)(?:.|[\\n\\r]){0,40}\\b([0-9]{6}-[0-9a-z]{8}-[0-9a-z]{4}-[0-9a-z]{4}-[0-9a-z]{4}-[0-9a-z]{12})\\b",
    "risk": "high",
    "entropy": 3.5
  },
  {
    "id": "github_token",
    "category": "api_key",
    "keywords": [
      "github"
    ],
    "regex": "\\b((?:ghp|gho|ghu|ghs|ghr)_[a-zA-Z0-9]{36,255})\\b",
    "risk": "high",
    "entropy": 3.5
  },
  {
    "id": "jira_token",
    "category": "api_key",
    "keywords": [
      "jira"
    ],
    "regex": "(?i)(?:jira)(?:.|[\\n\\r]){0,40}\\b([a-zA-Z-0-9]{24})\\b",
    "risk": "high",
    "entropy": 3.5
  },
  {
    "id": "mux_secret_token",
    "category": "api_key",
    "keywords": [],
    "regex": "(?i)(?:mux)(?:.|[\\n\\r]){0,40}([ \\r\\n]{0,1}[0-9A-Za-z\\/\\+]{75}[ \\r\\n]{1})",
    "risk": "high",
    "entropy": 3.5
  },
  {
    "id": "okta_api_token",
    "category": "api_key",
    "keywords": [
      "okta"
    ],
    "regex": "00[a-zA-Z0-9_-]{40}",
    "risk": "high",
    "entropy": 3.5
  },
  {
    "id": "onelogin_oauth_client_secret",
    "category": "api_key",
    "keywords": [
      "onelogin"
    ],
    "regex": "(?i)secret[a-zA-Z0-9_' \"=]{0,20}([a-z0-9]{64})",
    "risk": "high",
    "entropy": 3.5
  },
  {
    "id": "paypal/braintree_access_token",
    "category": "api_key",
    "keywords": [
      "paypal/braintree"
    ],
    "regex": "access_token\\$production\\$[0-9a-z]{16}\\$[0-9a-f]{32}",
    "risk": "high",
    "entropy": 3.5
  },
  {
    "id": "runrunit_api_user_token",
    "category": "api_key",
    "keywords": [
      "runrunit"
    ],
    "regex": "(?i)(?:runrunit)(?:.|[\\n\\r]){0,40}\\b([0-9A-Za-z]{18,20})\\b",
    "risk": "high",
    "entropy": 3.5
  },
  {
    "id": "sentiment_api_token",
    "category": "api_key",
    "keywords": [
      "sentiment"
    ],
    "regex": "(?i)(?:sentiment)(?:.|[\\n\\r]){0,40}\\b([a-zA-Z0-9]{20})\\b",
    "risk": "high",
    "entropy": 3.5
  },
  {
    "id": "slack_token",
    "category": "api_key",
    "keywords": [
      "slack"
    ],
    "regex": "(?:xoxb|xoxp|xapp|xoxa|xoxr)\\-[0-9]{10,13}\\-[a-zA-Z0-9\\-]*",
    "risk": "high",
    "entropy": 3.5
  },
  {
    "id": "slack_token_v2",
    "category": "api_key",
    "keywords": [
      "slack"
    ],
    "regex": "xox[baprs]-([0-9a-zA-Z]{10,48})?",
    "risk": "high"
  },
  {
    "id": "square_access_token",
    "category": "api_key",
    "keywords": [
      "square"
    ],
    "regex": "sq0atp-[0-9A-Za-z\\-_]{22}",
    "risk": "high",
    "entropy": 3.5
  },
  {
    "id": "square_oauth_secret",
    "category": "api_key",
    "keywords": [
      "square"
    ],
    "regex": "sq0csp-[0-9A-Za-z\\-_]{43}",
    "risk": "high",
    "entropy": 3.5
  },
  {
    "id": "teamgate_api_token",
    "category": "api_key",
    "keywords": [
      "teamgate"
    ],
    "regex": "(?i)(?:teamgate)(?:.|[\\n\\r]){0,40}\\b([a-z0-9]{40})\\b",
    "risk": "high",
    "entropy": 3.5
  },
  {
    "id": "telegram_api_token",
    "category": "api_key",
    "keywords": [
      "telegram"
    ],
    "regex": "(?i)(?:telegram)(?:.|[\\n\\r]){0,40}\\b([0-9]{8,12}:[a-zA-Z0-9_-]{35})\\b",
    "risk": "high",
    "entropy": 3.5
  },
  {
    "id": "twitter_access_token",
    "category": "api_key",
    "keywords": [
      "twitter"
    ],
    "regex": "(?i)(?:twitter)(?:.|[\\n\\r]){0,40}\\b[1-9][0-9]+-[0-9a-zA-Z]{40}\\b",
    "risk": "high",
    "entropy": 3.5
  },
  {
    "id": "zendesk_api_token",
    "category": "api_key",
    "keywords": [
      "zendesk"
    ],
    "regex": "(?i)(?:zendesk)(?:.|[\\n\\r]){0,40}([A-Za-z0-9_-]{40})",
    "risk": "high",
    "entropy": 3.5
  },
  {
    "id": "jwt",
    "category": "tokens",
    "keywords": [],
    "regex": "(?:[^0-9A-Za-z_.-]|\\A)(e(?:y[IJ]|yL[CD]|yA[JKgi]|w[ko][JKgi])[A-Za-z0-9_-]{10,}(?:fQ|[3HXn]0|[1BFJNRVZdhlpx]9)={0,2}\\.e(?:y[IJ]|yL[CD]|yA[JKgi]|w[ko][JKgi])[A-Za-z0-9_-]{10,}(?:fQ|[3HXn]0|[1BFJNRVZdhlpx]9)={0,2}(?:\\.?[A-Za-z0-9_-]+={0,2})?)(?:[^0-9A-Za-z_.=-]|\\z)",
    "risk": "high",
    "entropy": 3.5
  },
  {
    "id": "grafana_api_token",
    "category": "tokens",
    "keywords": [
      "grafana",
      "token"
    ],
    "regex": "(eyJrIjoi[A-Za-z0-9_=-]{42})",
    "risk": "high",
    "entropy": 3.5
  },
  {
    "id": "sentry_auth_token",
    "category": "tokens",
    "keywords": [
      "sentry",
      "auth",
      "token"
    ],
    "regex": "(?:(?:(?:\\A|[\\r\\n])\\[auth\\][^[]*\\ntoken\\s*=|(?:\\A|\\b)SENTRY_AUTH_TOKEN\\s*=|(?:\\A|\\b)sentry-cli [^\\r\\n]*--auth-token |(?:\\A|\\b)auth\\.token\\s*=)\\s*['\"`]?)([a-fA-F0-9]{64})(?:\\z|\\s|['\"`])",
    "risk": "high",
    "entropy": 3.5
  },
  {
    "id": "sentry_webpack_plugin_token",
    "category": "tokens",
    "keywords": [
      "sentry",
      "webpack",
      "plugin"
    ],
    "regex": "(?:new SentryPlugin\\(\\s*\\{[^}]*[,\\n \\t]apiKey:\\s*['\"])((?:[a-fA-F0-9]{32}|[a-fA-F0-9]{64}))(?:['\"])",
    "risk": "high",
    "entropy": 3.5
  },
  {
    "id": "sentry_terraform_provider_token",
    "category": "tokens",
    "keywords": [
      "sentry",
      "terraform",
      "provider"
    ],
    "regex": "(?:(?:\\A|[\\r\\n])provider \"sentry\" {[^}]*[\\n \\t]token\\s*=\\s*['\"])([a-fA-F0-9]{64})(?:['\"])",
    "risk": "high",
    "entropy": 3.5
  },
  {
    "id": "okta_token",
    "category": "tokens",
    "keywords": [
      "okta",
      "token"
    ],
    "regex": "(?:(\\A|[^0-9A-Za-z_+/-]))((0{2}[0-9A-Za-z_-]{40}))(?:(\\z|[^0-9A-Za-z_+/=-]))",
    "risk": "high",
    "entropy": 3.5
  },
  {
    "id": "flickr_oauth_token",
    "category": "tokens",
    "keywords": [
      "flickr",
      "oauth",
      "token"
    ],
    "regex": "(?:(\\A|\\b)oauth_token=)([0-9]{17}-[0-9a-f]{16})(?:\\z|\\b)",
    "risk": "high",
    "entropy": 3.5
  },
  {
    "id": "browserstack_token_url",
    "category": "tokens",
    "keywords": [
      "browserstack",
      "token"
    ],
    "regex": "(?:https?://)([^:]+:[0-9a-zA-Z]{20})(?:@hub-cloud\\.browserstack\\.com/)",
    "risk": "high"
  },
  {
    "id": "vercel_access_token_imprecise",
    "category": "tokens",
    "keywords": [
      "vercel",
      "access",
      "token"
    ],
    "regex": "(?:(\\A|\\b|[_.-])(?i)vercel[_.-]?((access|api)[_.-]?)?token\\s*[=:]\\s*['\"]?)([A-Za-z0-9]{24})(?:\\z|\\s|['\"])",
    "risk": "high",
    "entropy": 3.5
  },
  {
    "id": "vercel_access_token",
    "category": "tokens",
    "keywords": [
      "vercel",
      "access",
      "token"
    ],
    "regex": "(?:(\\A|\\b)(?i)vercel[_.-]?((access|api)[_.-]?)?token\\s*[=:]\\s*['\"]?)([A-Za-z0-9]{24})(?:\\z|\\s|['\"])",
    "risk": "high",
    "entropy": 3.5
  },
  {
    "id": "vercel_cli_token",
    "category": "tokens",
    "keywords": [
      "vercel",
      "token"
    ],
    "regex": "(?:(\\A|\\b)vercel [^\\r\\n]*--token=)([A-Za-z0-9]{24})(?:\\z|\\s)",
    "risk": "high",
    "entropy": 3.5
  },
  {
    "id": "jenkins_api_token",
    "category": "tokens",
    "keywords": [
      "jenkins",
      "token"
    ],
    "regex": "(?:(?i)jenkins_?(api[_-]?)?(token|secret|key)['\"`]?(\\s*[\\]\\)])?\\s*([:,=]|[=-]>|to|[!=]={1,2}|<>)?\\s*([[{])?['\"`]?)([a-f0-9]{32,64})(?:['\"`\\r\\n,]|\\z)",
    "risk": "high",
    "entropy": 3.5
  },
  {
    "id": "circleci_api_token",
    "category": "tokens",
    "keywords": [
      "circleci",
      "token"
    ],
    "regex": "(?:(?i)circle[_-]?(ci[_.-]?)?(api[_.-]?)?(token|key)['\"`]?(\\s*[\\]\\)])?\\s*([:,=]|[=-]>|to|[!=]={1,2}|<>)?\\s*([[{])?['\"`]?)([a-f0-9]{40})(?:['\"`\\r\\n,]|\\z)",
    "risk": "high",
    "entropy": 3.5
  },
  {
    "id": "yaml_token",
    "category": "tokens",
    "keywords": [
      "yaml",
      "with",
      "token"
    ],
    "regex": "(?:(?:\\n|\\A)[ \\t]*(?i)[a-z_-]*(?:secret|service_pass(wd|word|code|phrase)|pass(?:wd|word|code|phrase)?|key|token)[ \\t]*:[ \\t]*(['\"]?|[|>]-?[ \\t]*\\n[ \\t]*))([0-9a-f]{32}|[0-9a-f]{40}|[0-9a-f]{64})(?:['\"\\r\\n]|\\z)",
    "risk": "high",
    "entropy": 3.5
  },
  {
    "id": "bearer_tokens",
    "category": "tokens",
    "keywords": [
      "bearer",
      "tokens"
    ],
    "regex": "(?:(Authorization: |['\"])([Bb]earer |[Tt]oken (token=)?))([a-zA-Z0-9_.=/+:-]{12,})(?:\\z|[\\s'\"])",
    "risk": "high",
    "entropy": 3.5
  }
]